mensajes/__init__.py
mensajes/adios/__init__.py
mensajes/adios/despedidas.py
mensajes/hola/__init__.py
mensajes/hola/saludo.py
tests/__init__.py
tests/test_hola.py
Mensajes_RoollAvendano-7.0.dist-info/LICENSE
Mensajes_RoollAvendano-7.0.dist-info/METADATA
Mensajes_RoollAvendano-7.0.dist-info/WHEEL
Mensajes_RoollAvendano-7.0.dist-info/top_level.txt
Mensajes_RoollAvendano-7.0.dist-info/RECORD
